[
  {
    "column1": "1013823568",
    "column2": "691172870000938496",
    "column3": "7.136420902355329E307",
    "column4": "1.525255E38",
    "column5": "1915",
    "column6": "3zvmlcw",
    "column7": "true"
  },
  {
    "column1": "149284607",
    "column2": "3800866729381150720",
    "column3": "7.602382871558858E307",
    "column4": "3.007678E38",
    "column5": "19760",
    "column6": "fwiqhdo",
    "column7": "true"
  },
  {
    "column1": "998868574",
    "column2": "3634263377763832832",
    "column3": "1.5031774642242469E308",
    "column4": "1.7622735E37",
    "column5": "12001",
    "column6": "whqe0jdg2v4n",
    "column7": "false"
  },
  {
    "column1": "1755942049",
    "column2": "9157788252627866624",
    "column3": "1.3129654708937224E308",
    "column4": "2.6538527E38",
    "column5": "8296",
    "column6": "k6ip8",
    "column7": "true"
  },
  {
    "column1": "1927345052",
    "column2": "5813645749101530112",
    "column3": "8.672714884798315E307",
    "column4": "2.0334375E38",
    "column5": "10151",
    "column6": "za57eju",
    "column7": "false"
  },
  {
    "column1": "1020382427",
    "column2": "3829005780570150912",
    "column3": "1.0711981055778723E308",
    "column4": "2.8892065E38",
    "column5": "6518",
    "column6": "ikd0ezpq",
    "column7": "false"
  },
  {
    "column1": "626468456",
    "column2": "7999374557194277888",
    "column3": "4.904696379566789E307",
    "column4": "1.5288952E38",
    "column5": "3658",
    "column6": "z43kx",
    "column7": "true"
  },
  {
    "column1": "511042060",
    "column2": "972675887312241792",
    "column3": "6.268658139711785E307",
    "column4": "2.1688839E38",
    "column5": "10138",
    "column6": "wgr36of",
    "column7": "true"
  },
  {
    "column1": "845235989",
    "column2": "1915900958564621824",
    "column3": "4.056243334694153E307",
    "column4": "2.290868E38",
    "column5": "30858",
    "column6": "ms1vi",
    "column7": "false"
  },
  {
    "column1": "210954331",
    "column2": "602011839906277760",
    "column3": "3.9174144425619876E307",
    "column4": "1.3996369E38",
    "column5": "31218",
    "column6": "ecus8bi1ol",
    "column7": "true"
  }
]